magic_extract/__init__.py
magic_extract/test_basic.py
magic_extract-0.3.0.dist-info/LICENSE
magic_extract-0.3.0.dist-info/METADATA
magic_extract-0.3.0.dist-info/WHEEL
magic_extract-0.3.0.dist-info/top_level.txt
magic_extract-0.3.0.dist-info/RECORD
